{
  "timestamp": "2025-09-26T18:45:00",
  "type": "meta_pattern",
  "discovery": "AGET-AGET itself is a replicable pattern",
  "insight": {
    "core": "Every serious AGET contributor will create their own aget-aget",
    "reason": "Natural need for private experimentation space before contributing",
    "evidence": "GM created aget-aget for pattern extraction",
    "prediction": "Distributed governance emerges naturally"
  },
  "pattern": {
    "name": "Private Governance Layer",
    "description": "Create personal/organizational aget-aget for experimentation",
    "structure": {
      "public": "aget-cli-agent-template (shared commons)",
      "private": "[user]/aget-aget (individual labs)",
      "flow": "Experiment privately → Validate → Contribute publicly"
    },
    "benefits": [
      "Safe experimentation space",
      "Competitive advantage preservation",
      "Quality filter for public contributions",
      "Distributed innovation"
    ]
  },
  "network_effects": {
    "current": "Single user (GM) with private governance",
    "near_future": "Multiple users with private aget-agets",
    "evolution": "Network of private labs feeding public commons",
    "ultimate": "Mesh network of governance layers"
  },
  "implications": {
    "for_template": {
      "becomes": "True commons",
      "fed_by": "Many private labs",
      "quality": "Pre-validated patterns only",
      "governance": "Community-driven"
    },
    "for_users": {
      "empowerment": "Each user becomes a researcher",
      "freedom": "Experiment without public scrutiny",
      "contribution": "Share only what they want",
      "learning": "Private space for failure"
    }
  },
  "action_required": {
    "document_pattern": "Add 'Creating Your Governance Layer' to template",
    "provide_starter": "aget-aget starter template",
    "share_vision": "Encourage distributed governance",
    "celebrate": "Highlight successful aget-aget instances"
  },
  "philosophical_shift": {
    "from": "Central governance",
    "to": "Distributed experimentation",
    "metaphor": "Every gardener needs a greenhouse",
    "result": "Cambrian explosion of patterns"
  },
  "success_metrics": [
    "Number of aget-aget repos in wild",
    "Quality of pattern contributions",
    "Diversity of patterns",
    "Innovation velocity"
  ],
  "humor": "Someone will eventually create aget-aget-aget for governing governance layers"
}